fb_rate_limiter/__init__.py
facebook_api_rate_limiter-0.0.1.dist-info/LICENSE
facebook_api_rate_limiter-0.0.1.dist-info/METADATA
facebook_api_rate_limiter-0.0.1.dist-info/WHEEL
facebook_api_rate_limiter-0.0.1.dist-info/top_level.txt
facebook_api_rate_limiter-0.0.1.dist-info/RECORD
